{"is_source_file": false, "format": "", "description": "", "external_files": [], "external_methods": [], "published": [], "classes": [], "methods": [], "calls": [], "search-terms": [], "state": 2, "file_id": 39, "knowledge_revision": 83, "git_revision": "7de2ec4cf899e49409bb1b656b0e67ed808e97c8", "hash": "72c0b669501baf568cb32543d5cdbd6c", "format-version": 4, "code-base-name": "recipe_frontend", "filename": "recipe_frontend/src/app/app.component.html", "revision_history": [{"83": "7de2ec4cf899e49409bb1b656b0e67ed808e97c8"}]}