{"is_source_file": true, "format": "TypeScript", "description": "This file defines an Angular service class 'SupabaseService' that encapsulates the creation and initialization of a Supabase client instance, using environment variables for configuration.", "external_files": ["node_modules/@supabase/supabase-js/dist/supabase-js.js"], "external_methods": ["createClient"], "published": ["SupabaseService"], "classes": [{"name": "SupabaseService", "description": "An Angular injectable service that provides a configured Supabase client instance for use throughout the application."}], "methods": [{"name": "constructor() { constructor", "description": "Initializes the Supabase client using environment variables for URL and key, supporting both process.env and globalThis for flexibility.", "scope": "SupabaseService", "scopeKind": "class"}], "calls": ["createClient"], "search-terms": ["SupabaseService", "Angular", "Supabase", "createClient", "environment variables"], "state": 2, "file_id": 23, "knowledge_revision": 100, "git_revision": "", "revision_history": [{"47": ""}, {"93": ""}, {"100": ""}], "ctags": [{"_type": "tag", "name": "SupabaseService", "path": "/home/kavia/workspace/code-generation/recipe-hub-13228-13248/recipe_frontend/src/app/services/supabase.service.ts", "pattern": "/^export class SupabaseService {$/", "language": "TypeScript", "kind": "class"}, {"_type": "tag", "name": "constructor", "path": "/home/kavia/workspace/code-generation/recipe-hub-13228-13248/recipe_frontend/src/app/services/supabase.service.ts", "pattern": "/^  constructor() {$/", "language": "TypeScript", "kind": "method", "scope": "SupabaseService", "scopeKind": "class"}, {"_type": "tag", "name": "key", "path": "/home/kavia/workspace/code-generation/recipe-hub-13228-13248/recipe_frontend/src/app/services/supabase.service.ts", "pattern": "/^    const key = (typeof process !== 'undefined' && process.env && process.env['NG_APP_SUPABASE_K/", "language": "TypeScript", "kind": "constant", "scope": "SupabaseService.constructor", "scopeKind": "method"}, {"_type": "tag", "name": "supabase", "path": "/home/kavia/workspace/code-generation/recipe-hub-13228-13248/recipe_frontend/src/app/services/supabase.service.ts", "pattern": "/^  public supabase: SupabaseClient;$/", "language": "TypeScript", "kind": "property", "scope": "SupabaseService", "scopeKind": "class"}, {"_type": "tag", "name": "url", "path": "/home/kavia/workspace/code-generation/recipe-hub-13228-13248/recipe_frontend/src/app/services/supabase.service.ts", "pattern": "/^    const url = (typeof process !== 'undefined' && process.env && process.env['NG_APP_SUPABASE_U/", "language": "TypeScript", "kind": "constant", "scope": "SupabaseService.constructor", "scopeKind": "method"}], "hash": "db72814189da6f176535fe134fe48029", "format-version": 4, "code-base-name": "recipe_frontend", "filename": "recipe_frontend/src/app/services/supabase.service.ts", "fields": [{"name": "public supabase: SupabaseClient;", "scope": "SupabaseService", "scopeKind": "class", "description": "unavailable"}]}